AUTHORS
Changelog
INSTALL
LICENSE
MANIFEST.in
README
README.rst
setup.cfg
setup.py
literal/__init__.py
literal.egg-info/PKG-INFO
literal.egg-info/SOURCES.txt
literal.egg-info/dependency_links.txt
literal.egg-info/not-zip-safe
literal.egg-info/top_level.txt